rootcanal/__init__.py
rootcanal/__main__.py
rootcanal/binaries.py
rootcanal/bluetooth.py
rootcanal/controller.py
rootcanal/bin/linux-x86_64/librootcanal_ffi.so
rootcanal/bin/linux-x86_64/rootcanal
rootcanal/packets/__init__.py
rootcanal/packets/hci.py
rootcanal/packets/ll.py
rootcanal/packets/llcp.py
rootcanal/packets/lmp.py
rootcanal-1.11.0.dist-info/METADATA
rootcanal-1.11.0.dist-info/WHEEL
rootcanal-1.11.0.dist-info/RECORD
