Metadata-Version: 2.4
Name: rootcanal
Version: 1.11.0
Summary: Virtual Bluetooth controller
Project-URL: Homepage, https://github.com/google/rootcanal
Project-URL: Bug Tracker, https://github.com/google/rootcanal/issues
Maintainer-email: Henri Chataing <henrichataing@google.com>, David Duarte <licorne@google.com>
License: Apache-2.0
Keywords: Bluetooth,Controller,Emulation
Classifier: License :: OSI Approved :: Apache Software License
Classifier: Operating System :: OS Independent
Classifier: Programming Language :: Python :: 3
Requires-Python: >=3.10
